geos18_nexrad_package/__init__.py
geos18_nexrad_package/cli.py
g18nex-1.dist-info/METADATA
g18nex-1.dist-info/WHEEL
g18nex-1.dist-info/entry_points.txt
g18nex-1.dist-info/top_level.txt
g18nex-1.dist-info/RECORD
