Metadata-Version: 2.1
Name: g18nex
Version: 1
Classifier: Programming Language :: Python :: 3
Classifier: License :: OSI Approved :: MIT License
Classifier: Operating System :: OS Independent
Requires-Dist: numpy
Requires-Dist: pandas
Requires-Dist: typer
Requires-Dist: requests
